{"blta9ded0a7f7f96a0b":{"stackHeaders":{"api_key":"blte09880fe3a41034c","branch":"main"},"urlPath":"/environments/development","urls":[{"locale":"en-us","url":"https://cs-academy-hanoak-1740463301-f43d5.vercel.app"}],"name":"development","_version":6,"uid":"blta9ded0a7f7f96a0b","created_by":"blt2992887479ec1a36","updated_by":"blt2992887479ec1a36","created_at":"2025-02-25T05:59:28.773Z","updated_at":"2025-02-25T06:02:33.868Z"},"bltc30f5a2b074192ba":{"stackHeaders":{"api_key":"blte09880fe3a41034c","branch":"main"},"urlPath":"/environments/preview","urls":[{"url":"","locale":"en-us"}],"name":"preview","_version":1,"uid":"bltc30f5a2b074192ba","created_by":"blt2992887479ec1a36","updated_by":"blt2992887479ec1a36","created_at":"2025-02-25T05:59:28.359Z","updated_at":"2025-02-25T05:59:28.359Z"},"bltd0a5efd4d108c694":{"stackHeaders":{"api_key":"blte09880fe3a41034c","branch":"main"},"urlPath":"/environments/production","urls":[{"url":"","locale":"en-us"}],"name":"production","_version":3,"uid":"bltd0a5efd4d108c694","created_by":"blt2992887479ec1a36","updated_by":"blt2992887479ec1a36","created_at":"2025-02-25T05:59:28.358Z","updated_at":"2025-02-25T05:59:28.358Z"}}